{
  "kind": "collectionType",
  "collectionName": "timelines",
  "info": {
    "singularName": "timeline",
    "pluralName": "timelines",
    "displayName": "Timeline",
    "description": ""
  },
  "options": {
    "draftAndPublish": true
  },
  "pluginOptions": {},
  "attributes": {
    "title": {
      "type": "string"
    },
    "description": {
      "type": "text"
    },
    "type": {
      "type": "enumeration",
      "enum": [
        "formation",
        "experience"
      ]
    },
    "startDate": {
      "type": "date"
    },
    "endDate": {
      "type": "date"
    },
    "logo": {
      "type": "media",
      "multiple": true,
      "required": false,
      "allowedTypes": [
        "images",
        "files",
        "videos",
        "audios"
      ]
    },
    "titleEn": {
      "type": "string"
    },
    "descriptionEn": {
      "type": "text"
    }
  }
}
